test/__init__.py
test/test_acl.py
test/test_author.py
test/test_author_inner.py
test/test_category.py
test/test_category_api.py
test/test_category_extended.py
test/test_file.py
test/test_file_api.py
test/test_post.py
test/test_post_api.py
test/test_tag.py
test/test_tag_api.py
website_python_client/__init__.py
website_python_client/api_client.py
website_python_client/configuration.py
website_python_client/rest.py
website_python_client/api/__init__.py
website_python_client/api/category_api.py
website_python_client/api/file_api.py
website_python_client/api/post_api.py
website_python_client/api/tag_api.py
website_python_client/models/__init__.py
website_python_client/models/acl.py
website_python_client/models/author.py
website_python_client/models/author_inner.py
website_python_client/models/category.py
website_python_client/models/category_extended.py
website_python_client/models/file.py
website_python_client/models/post.py
website_python_client/models/tag.py
felix_scholz_website_python_client-0.0.2.dist-info/LICENSE
felix_scholz_website_python_client-0.0.2.dist-info/METADATA
felix_scholz_website_python_client-0.0.2.dist-info/WHEEL
felix_scholz_website_python_client-0.0.2.dist-info/top_level.txt
felix_scholz_website_python_client-0.0.2.dist-info/RECORD
