Metadata-Version: 2.1
Name: felix-scholz-website-python-client
Version: 0.0.2
Summary: Client for Felix' Website
Home-page: UNKNOWN
Author: UNKNOWN
Author-email: felix@felix-scholz.org
License: UNKNOWN
Keywords: Swagger,Felix' Website mit Blog
Platform: UNKNOWN
Requires-Dist: urllib3 (>=1.15)
Requires-Dist: six (>=1.10)
Requires-Dist: certifi
Requires-Dist: python-dateutil
